setup.py
aws_ls/__init__.py
aws_ls/lib.py
aws_ls.egg-info/PKG-INFO
aws_ls.egg-info/SOURCES.txt
aws_ls.egg-info/dependency_links.txt
aws_ls.egg-info/entry_points.txt
aws_ls.egg-info/requires.txt
aws_ls.egg-info/top_level.txt