Metadata-Version: 1.0
Name: aws-ls
Version: 0.0.2
Summary: aws ls tools
Home-page: https://github.com/xxx
Author: elon
Author-email: iphone1945@126.com
License: GPL Licence
Keywords: aws
Platform: any
